restzzz/views.py
restzzz/zmqwrap.py
restzzz/__init__.py
restzzz-0.1.dist-info/DESCRIPTION.rst
restzzz-0.1.dist-info/WHEEL
restzzz-0.1.dist-info/top_level.txt
restzzz-0.1.dist-info/entry_points.txt
restzzz-0.1.dist-info/metadata.json
restzzz-0.1.dist-info/RECORD
restzzz-0.1.dist-info/METADATA
