Metadata-Version: 2.0
Name: restzzz
Version: 0.1
Summary: REST-ful API for 0mq
Home-page: http://code.msoucy.me/RESTZZZ
Author: Matt Soucy
Author-email: msoucy@csh.rit.edu
License: UNKNOWN
Keywords: web services
Platform: UNKNOWN
Classifier: Programming Language :: Python
Classifier: Framework :: Pylons
Classifier: Topic :: Internet :: WWW/HTTP
Classifier: Topic :: Internet :: WWW/HTTP :: WSGI :: Application
Requires-Dist: cornice
Requires-Dist: waitress
Requires-Dist: PyYAML
Requires-Dist: pyzmq
